{ "type": "FeatureCollection",
  "features": [{
    "type":"Feature",
    "geometry":{
      "type":"Point",
      "coordinates":[-97.77308111999969,30.191450819000465]
    },
      "properties":{
        "name":"test spot 1",
        "city":"Austin",
        "type":"parking garage"
      }
    },
    {
      "type":"Feature",
      "geometry":{
        "type":"Point",
        "coordinates":[-97.77308111999969,30.0000000000]
      },
        "properties":{
          "name":"test spot 2",
          "city":"Austin",
          "type":"driveway"
      }
    }
  ],
  "crs" : { "type": "name", "properties": { "name": "urn:ogc:def:crs:OGC:1.3:CRS84" } }
}